torchvert
